{
	"domain": "mobi",
	"registryOperator": "Identity Digital Domains Limited",
	"infoURL": "http://nic.mobi/",
	"whoisServer": "whois.nic.mobi",
	"rdapURLs": [
		"https://rdap.identitydigital.services/rdap/"
	],
	"nameServers": [
		"a0.mobi.afilias-nst.info",
		"a2.mobi.afilias-nst.info",
		"b0.mobi.afilias-nst.org",
		"b2.mobi.afilias-nst.org",
		"c0.mobi.afilias-nst.info",
		"d0.mobi.afilias-nst.org"
	],
	"languages": [
		"ar",
		"be",
		"bg",
		"bs-Cyrl",
		"cnr-Cyrl",
		"da",
		"de",
		"es",
		"fi",
		"fr",
		"hi",
		"hu",
		"is",
		"it",
		"ko",
		"lt",
		"lv",
		"mk",
		"pl",
		"pt",
		"ru",
		"sr-Cyrl",
		"sv",
		"uk",
		"zh",
		"zh-CN"
	],
	"tags": [
		"generic",
		"sponsored"
	],
	"policies": [
		{
			"type": "idn-table",
			"key": "ar",
			"value": "https://www.iana.org/domains/idn-tables/tables/mobi_ar_5.xml"
		},
		{
			"type": "idn-table",
			"key": "be",
			"value": "https://www.iana.org/domains/idn-tables/tables/mobi_be_5.xml"
		},
		{
			"type": "idn-table",
			"key": "bg",
			"value": "https://www.iana.org/domains/idn-tables/tables/mobi_bg_5.xml"
		},
		{
			"type": "idn-table",
			"key": "bs-Cyrl",
			"value": "https://www.iana.org/domains/idn-tables/tables/mobi_bs-cyrl_5.xml"
		},
		{
			"type": "idn-table",
			"key": "cnr-Cyrl",
			"value": "https://www.iana.org/domains/idn-tables/tables/mobi_cnr-cyrl_5.xml"
		},
		{
			"type": "idn-table",
			"key": "da",
			"value": "https://www.iana.org/domains/idn-tables/tables/mobi_da_5.xml"
		},
		{
			"type": "idn-table",
			"key": "de",
			"value": "https://www.iana.org/domains/idn-tables/tables/mobi_de_5.xml"
		},
		{
			"type": "idn-table",
			"key": "es",
			"value": "https://www.iana.org/domains/idn-tables/tables/mobi_es_5.xml"
		},
		{
			"type": "idn-table",
			"key": "fi",
			"value": "https://www.iana.org/domains/idn-tables/tables/mobi_fi_5.xml"
		},
		{
			"type": "idn-table",
			"key": "fr",
			"value": "https://www.iana.org/domains/idn-tables/tables/mobi_fr_5.xml"
		},
		{
			"type": "idn-table",
			"key": "hi",
			"value": "https://www.iana.org/domains/idn-tables/tables/mobi_hi_5.xml"
		},
		{
			"type": "idn-table",
			"key": "hu",
			"value": "https://www.iana.org/domains/idn-tables/tables/mobi_hu_5.xml"
		},
		{
			"type": "idn-table",
			"key": "is",
			"value": "https://www.iana.org/domains/idn-tables/tables/mobi_is_5.xml"
		},
		{
			"type": "idn-table",
			"key": "it",
			"value": "https://www.iana.org/domains/idn-tables/tables/mobi_it_5.xml"
		},
		{
			"type": "idn-table",
			"key": "ko",
			"value": "https://www.iana.org/domains/idn-tables/tables/mobi_ko_5.xml"
		},
		{
			"type": "idn-table",
			"key": "lt",
			"value": "https://www.iana.org/domains/idn-tables/tables/mobi_lt_5.xml"
		},
		{
			"type": "idn-table",
			"key": "lv",
			"value": "https://www.iana.org/domains/idn-tables/tables/mobi_lv_5.xml"
		},
		{
			"type": "idn-table",
			"key": "mk",
			"value": "https://www.iana.org/domains/idn-tables/tables/mobi_mk_5.xml"
		},
		{
			"type": "idn-table",
			"key": "pl",
			"value": "https://www.iana.org/domains/idn-tables/tables/mobi_pl_5.xml"
		},
		{
			"type": "idn-table",
			"key": "pt",
			"value": "https://www.iana.org/domains/idn-tables/tables/mobi_pt_5.xml"
		},
		{
			"type": "idn-table",
			"key": "ru",
			"value": "https://www.iana.org/domains/idn-tables/tables/mobi_ru_5.xml"
		},
		{
			"type": "idn-table",
			"key": "sr-Cyrl",
			"value": "https://www.iana.org/domains/idn-tables/tables/mobi_sr-cyrl_5.xml"
		},
		{
			"type": "idn-table",
			"key": "sv",
			"value": "https://www.iana.org/domains/idn-tables/tables/mobi_sv_5.xml"
		},
		{
			"type": "idn-table",
			"key": "uk",
			"value": "https://www.iana.org/domains/idn-tables/tables/mobi_uk_5.xml"
		},
		{
			"type": "idn-table",
			"key": "zh",
			"value": "https://www.iana.org/domains/idn-tables/tables/mobi_zh_5.xml"
		},
		{
			"type": "idn-table",
			"key": "zh-CN",
			"value": "https://www.iana.org/domains/idn-tables/tables/mobi_zh-cn_4.1.txt"
		}
	]
}
