{
	"domain": "nico",
	"registryOperator": "DWANGO Co., Ltd.",
	"infoURL": "https://nic.nico/",
	"whoisServer": "whois.nic.nico",
	"rdapURLs": [
		"https://rdap.gmoregistry.net/rdap/"
	],
	"nameServers": [
		"a.gmoregistry.net",
		"b.gmoregistry.net",
		"k.gmoregistry.net",
		"l.gmoregistry.net"
	],
	"languages": [
		"ja"
	],
	"tags": [
		"brand",
		"generic"
	],
	"policies": [
		{
			"type": "idn-table",
			"key": "ja",
			"value": "https://www.iana.org/domains/idn-tables/tables/nico_ja_1.0.txt"
		}
	]
}
