{
	"domain": "rw",
	"registryOperator": "Rwanda Internet Community and Technology  Alliance (RICTA) Ltd",
	"countryName": "Rwanda",
	"infoURL": "https://ricta.org.rw/",
	"whoisServer": "whois.ricta.org.rw",
	"rdapURLs": [
		"https://rdap.ricta.org.rw/"
	],
	"nameServers": [
		"dnsnode.ricta.org.rw",
		"ns-afrinic.ricta.org.rw",
		"ns1.gransy.ricta.org.rw",
		"ns1.ricta.org.rw",
		"ns2.ricta.org.rw",
		"ns3.ricta.org.rw",
		"pch.ricta.org.rw"
	],
	"tags": [
		"country",
		"geo"
	],
	"policies": [
		{
			"type": "idn-disallowed"
		}
	]
}
