{
	"domain": "sas",
	"registryOperator": "Research IP LLC",
	"infoURL": "https://newgtlds.icann.org/",
	"whoisServer": "whois.nic.sas",
	"rdapURLs": [
		"https://rdap.nic.sas/"
	],
	"nameServers": [
		"a.nic.sas",
		"b.nic.sas",
		"c.nic.sas",
		"ns1.dns.nic.sas",
		"ns2.dns.nic.sas",
		"ns3.dns.nic.sas"
	],
	"languages": [
		"es"
	],
	"tags": [
		"brand",
		"generic"
	],
	"policies": [
		{
			"type": "idn-table",
			"key": "es",
			"value": "https://www.iana.org/domains/idn-tables/tables/sas_es_3.0.xml"
		}
	]
}
