{
	"domain": "sky",
	"registryOperator": "Sky International AG",
	"infoURL": "https://www.skygroup.sky/nic-sky",
	"whoisServer": "whois.nic.sky",
	"rdapURLs": [
		"https://tld-rdap.verisign.com/sky/v1/"
	],
	"nameServers": [
		"ac1.nstld.com",
		"ac2.nstld.com",
		"ac3.nstld.com",
		"ac4.nstld.com"
	],
	"languages": [
		"mul-Arab",
		"mul-Latn"
	],
	"tags": [
		"brand",
		"generic"
	],
	"policies": [
		{
			"type": "idn-table",
			"key": "mul-Arab",
			"value": "https://www.iana.org/domains/idn-tables/tables/sky_arab_2.5.txt"
		},
		{
			"type": "idn-table",
			"key": "mul-Latn",
			"value": "https://www.iana.org/domains/idn-tables/tables/sky_latn_2.5.txt"
		}
	]
}
